odoo10_addon_l10n_es_account_fiscal_year_closing-10.0.1.0.0-py2.7-nspkg.pth
odoo/addons/l10n_es_account_fiscal_year_closing/README.rst
odoo/addons/l10n_es_account_fiscal_year_closing/__init__.py
odoo/addons/l10n_es_account_fiscal_year_closing/__manifest__.py
odoo/addons/l10n_es_account_fiscal_year_closing/data/account_fiscal_year_closing_data_big.xml
odoo/addons/l10n_es_account_fiscal_year_closing/data/account_fiscal_year_closing_data_sme_ngo.xml
odoo/addons/l10n_es_account_fiscal_year_closing/i18n/es.po
odoo/addons/l10n_es_account_fiscal_year_closing/static/description/icon.png
odoo/addons/l10n_es_account_fiscal_year_closing/static/description/icon.svg
odoo10_addon_l10n_es_account_fiscal_year_closing-10.0.1.0.0.dist-info/DESCRIPTION.rst
odoo10_addon_l10n_es_account_fiscal_year_closing-10.0.1.0.0.dist-info/METADATA
odoo10_addon_l10n_es_account_fiscal_year_closing-10.0.1.0.0.dist-info/RECORD
odoo10_addon_l10n_es_account_fiscal_year_closing-10.0.1.0.0.dist-info/WHEEL
odoo10_addon_l10n_es_account_fiscal_year_closing-10.0.1.0.0.dist-info/metadata.json
odoo10_addon_l10n_es_account_fiscal_year_closing-10.0.1.0.0.dist-info/namespace_packages.txt
odoo10_addon_l10n_es_account_fiscal_year_closing-10.0.1.0.0.dist-info/top_level.txt
